ksuid/__init__.py
ksuid/base62.py
ksuid/ksuid.py
ksuid/utils.py
pyksuid-1.3.dist-info/LICENSE
pyksuid-1.3.dist-info/METADATA
pyksuid-1.3.dist-info/WHEEL
pyksuid-1.3.dist-info/top_level.txt
pyksuid-1.3.dist-info/RECORD
