Metadata-Version: 2.1
Name: pyksuid
Version: 1.3
Summary: A small python package for creating ksuids
Home-page: https://github.com/zaghaghi/KSUID
Author: Samuel Resendez
Author-email: samresendez1@gmail.com
License: MIT
Platform: UNKNOWN
License-File: LICENSE
